mdformat_config/__init__.py
mdformat_config-0.2.1.dist-info/LICENSE
mdformat_config-0.2.1.dist-info/METADATA
mdformat_config-0.2.1.dist-info/WHEEL
mdformat_config-0.2.1.dist-info/entry_points.txt
mdformat_config-0.2.1.dist-info/RECORD
